{"batch_size_train": 64, "batch_size_test": 512, "in_type": "normal", "rnn_type": "LeakyRNN", "use_separate_input": false, "loss_type": "lsq", "optimizer": "adam", "activation": "softplus", "tau": 100, "dt": 20, "alpha": 0.2, "sigma_rec": 0.05, "sigma_x": 0.01, "w_rec_init": "randortho", "l1_h": 0.0, "l2_h": 0, "l1_weight": 0, "l2_weight": 0, "l2_weight_init": 0, "p_weight_train": null, "target_perf": 0.995, "mature_target_perf": 0.95, "mid_target_perf": 0.65, "early_target_perf": 0.35, "n_eachring": 8, "num_ring": 3, "n_rule": 7, "rule_start": 25, "n_input": 32, "n_output": 9, "n_rnn": 256, "ruleset": "MNM_color_6tasks", "save_name": "test", "learning_rate": 0.001, "c_intsyn": 0, "ksi_intsyn": 0, "mix_rule": true, "seed": 0, "rule_trains": ["MNM_color", "overlap", "zero_gap", "gap", "odr", "odrd", "gap500"], "rules": ["MNM_color", "overlap", "zero_gap", "gap", "odr", "odrd", "gap500"], "rule_probs": [0.14285714285714285, 0.14285714285714285, 0.14285714285714285, 0.14285714285714285, 0.14285714285714285, 0.14285714285714285, 0.14285714285714285]}